MANIFEST.in
README.txt
setup.cfg
setup.py
art/__init__.py
art.mashup.egg-info/PKG-INFO
art.mashup.egg-info/SOURCES.txt
art.mashup.egg-info/dependency_links.txt
art.mashup.egg-info/entry_points.txt
art.mashup.egg-info/namespace_packages.txt
art.mashup.egg-info/not-zip-safe
art.mashup.egg-info/paster_plugins.txt
art.mashup.egg-info/requires.txt
art.mashup.egg-info/top_level.txt
art/mashup/README.txt
art/mashup/__init__.py
art/mashup/artlib.py
art/mashup/config.py
art/mashup/configure.zcml
art/mashup/i18n.sh
art/mashup/_backup/_110403_artlib.py
art/mashup/browser/__init__.py
art/mashup/browser/configure.zcml
art/mashup/browser/external_page_view.pt
art/mashup/browser/title.pt
art/mashup/browser/viewlets.py
art/mashup/browser/views.py
art/mashup/browser/web_service_result_viewlet.pt
art/mashup/browser/web_service_view.pt
art/mashup/browser/xml_document_content_viewlet.pt
art/mashup/browser/xml_document_view.pt
art/mashup/content/__init__.py
art/mashup/content/configure.zcml
art/mashup/content/externalpage.py
art/mashup/content/validators.py
art/mashup/content/webserviceclient.py
art/mashup/content/xmldocument.py
art/mashup/content/_backup/_110917_xmldocument.py
art/mashup/content/_backup/_110929_xmldocument.py
art/mashup/interfaces/__init__.py
art/mashup/interfaces/externalpage.py
art/mashup/interfaces/webserviceclient.py
art/mashup/interfaces/xmldocument.py
art/mashup/locales/art.mashup.pot
art/mashup/locales/de/LC_MESSAGES/README.txt
art/mashup/locales/de/LC_MESSAGES/art.mashup.mo
art/mashup/locales/de/LC_MESSAGES/art.mashup.po
art/mashup/locales/en/LC_MESSAGES/README.txt
art/mashup/locales/en/LC_MESSAGES/art.mashup.mo
art/mashup/locales/en/LC_MESSAGES/art.mashup.po
art/mashup/locales/it/LC_MESSAGES/README.txt
art/mashup/locales/it/LC_MESSAGES/art.mashup.mo
art/mashup/locales/it/LC_MESSAGES/art.mashup.po
art/mashup/portlets/__init__.py
art/mashup/portlets/configure.zcml
art/mashup/profiles/default/factorytool.xml
art/mashup/profiles/default/metadata.xml
art/mashup/profiles/default/portlets.xml
art/mashup/profiles/default/rolemap.xml
art/mashup/profiles/default/types.xml
art/mashup/profiles/default/viewlets.xml
art/mashup/profiles/default/types/External_Page.xml
art/mashup/profiles/default/types/Web_Service_Client.xml
art/mashup/profiles/default/types/XML_Document.xml
