Metadata-Version: 1.0
Name: art.mashup
Version: 1.0
Summary: Viewing of external contents
Home-page: http://svn.plone.org/svn/collective/
Author: Paolo Betti
Author-email: paolo@artifex.it
License: GPL
Platform: UNKNOWN
Classifier: Framework :: Plone
Classifier: Intended Audience :: Developers
Classifier: License :: OSI Approved :: GNU General Public License (GPL)
